symosi/__init__.py
symosi/components.py
symosi/core.py
symosi/sources.py
symosi-1.0.dist-info/LICENSE.txt
symosi-1.0.dist-info/METADATA
symosi-1.0.dist-info/WHEEL
symosi-1.0.dist-info/top_level.txt
symosi-1.0.dist-info/RECORD
