Metadata-Version: 2.1
Name: symosi
Version: 1.0
Summary: Python System Model Simulation Library
Home-page: UNKNOWN
Author: hramon
License: UNKNOWN
Platform: UNKNOWN
Requires-Dist: numpy
Requires-Dist: scipy
